[
  {
    "id": 1768219461905,
    "sender": "127.0.0.1",
    "senderId": "1768216327110",
    "senderName": "tamizuddin",
    "senderRole": "admin",
    "text": "hi",
    "timestamp": "2026-01-12T12:04:21.905Z",
    "deleted": false
  },
  {
    "id": 1768297917300,
    "sender": "127.0.0.1",
    "senderId": "1768216327110",
    "senderName": "Tamiz Uddin",
    "senderRole": "admin",
    "text": "hey",
    "communityId": "comm_1768297896508",
    "timestamp": "2026-01-13T09:51:57.300Z",
    "deleted": false
  }
]